taichi_big_float/__init__.py
taichi_big_float/ast_transformer.py
taichi_big_float/float_n32_p2.py
taichi_big_float/mantissa_n32.py
taichi_big_float-0.1.3.dist-info/METADATA
taichi_big_float-0.1.3.dist-info/WHEEL
taichi_big_float-0.1.3.dist-info/top_level.txt
taichi_big_float-0.1.3.dist-info/RECORD
