Metadata-Version: 2.4
Name: taichi-big-float
Version: 0.1.3
Summary: Multiprecision type extension for taichi
Author-email: Balázs Szalai <balazs.backup.2@gmail.com>
Project-URL: Homepage, https://github.com/balazs-szalai/taichi-bigfloat/
Requires-Python: >=3.8
Requires-Dist: taichi>=1.7
Requires-Dist: mpmath
